adversarial_labeller/__init__.py
adversarial_labeller/adversarial_labeller.py
adversarial_labeller/adversarial_scoring.py
adversarial_labeller-0.1.8.dist-info/LICENSE
adversarial_labeller-0.1.8.dist-info/METADATA
adversarial_labeller-0.1.8.dist-info/WHEEL
adversarial_labeller-0.1.8.dist-info/top_level.txt
adversarial_labeller-0.1.8.dist-info/RECORD
