Metadata-Version: 2.1
Name: adversarial-labeller
Version: 0.1.8
Summary: Sklearn compatiable model instance labelling tool to help validate models in situations involving data drift.
Home-page: https://github.com/robinsonkwame/adversarial_labeller
Author: Kwame Porter Robinson
Author-email: kwamepr@umich.edu
License: MIT license
Keywords: model selection,validation,data drift
Platform: UNKNOWN
Classifier: Development Status :: 2 - Pre-Alpha
Classifier: Intended Audience :: Developers
Classifier: License :: OSI Approved :: MIT License
Classifier: Natural Language :: English
Classifier: Programming Language :: Python :: 3
Classifier: Programming Language :: Python :: 3.7
Requires-Dist: attrs (==19.3.0)
Requires-Dist: bleach (==3.1.0)
Requires-Dist: certifi (==2019.11.28)
Requires-Dist: cffi (==1.13.2)
Requires-Dist: chardet (==3.0.4)
Requires-Dist: cryptography (==2.8)
Requires-Dist: docutils (==0.15.2)
Requires-Dist: idna (==2.8)
Requires-Dist: imbalanced-learn (==0.6.1)
Requires-Dist: jeepney (==0.4.1)
Requires-Dist: joblib (==0.14.1)
Requires-Dist: keyring (==21.0.0)
Requires-Dist: more-itertools (==8.0.2)
Requires-Dist: numpy (==1.18.0)
Requires-Dist: packaging (==19.2)
Requires-Dist: pandas (==0.25.3)
Requires-Dist: pkginfo (==1.5.0.1)
Requires-Dist: pluggy (==0.13.1)
Requires-Dist: py (==1.8.1)
Requires-Dist: pycparser (==2.19)
Requires-Dist: pygments (==2.5.2)
Requires-Dist: pyparsing (==2.4.6)
Requires-Dist: pytest (==5.3.2)
Requires-Dist: python-dateutil (==2.8.1)
Requires-Dist: pytz (==2019.3)
Requires-Dist: readme-renderer (==24.0)
Requires-Dist: requests-toolbelt (==0.9.1)
Requires-Dist: requests (==2.22.0)
Requires-Dist: scikit-learn (==0.22)
Requires-Dist: scipy (==1.4.1)
Requires-Dist: six (==1.13.0)
Requires-Dist: sklearn (==0.0)
Requires-Dist: tqdm (==4.41.0)
Requires-Dist: twine (==3.1.1)
Requires-Dist: urllib3 (==1.25.7)
Requires-Dist: wcwidth (==0.1.7)
Requires-Dist: webencodings (==0.5.1)
Requires-Dist: zipp (==0.6.0)
Requires-Dist: importlib-metadata (==1.3.0) ; python_version < "3.8"
Requires-Dist: secretstorage (==3.1.1) ; sys_platform == "linux"
